rlf/__init__.py
rlf/core.py
rlfe-0.1.0.dist-info/METADATA
rlfe-0.1.0.dist-info/WHEEL
rlfe-0.1.0.dist-info/top_level.txt
rlfe-0.1.0.dist-info/RECORD
